config_binder/__init__.py
config_binder/binder.py
config_binder-0.4.1.dist-info/LICENSE
config_binder-0.4.1.dist-info/METADATA
config_binder-0.4.1.dist-info/WHEEL
config_binder-0.4.1.dist-info/RECORD
