Metadata-Version: 2.1
Name: config-binder
Version: 0.4.1
Summary: Easily parse configurations across various formats (YAML, JSON, etc.) with recursive class binding, environment variables resolution and type safety.
License: MIT
Author: Pavel Istomin
Author-email: inspaulation@gmail.com
Requires-Python: >=3.8,<4.0
Classifier: License :: OSI Approved :: MIT License
Classifier: Programming Language :: Python :: 3
Classifier: Programming Language :: Python :: 3.8
Classifier: Programming Language :: Python :: 3.9
Classifier: Programming Language :: Python :: 3.10
Classifier: Programming Language :: Python :: 3.11
Classifier: Programming Language :: Python :: 3.12
Requires-Dist: pydantic (>=2.9.2,<3.0.0)
Requires-Dist: pyyaml (>=6.0,<7.0)
